Metadata-Version: 2.1
Name: seleniumGoogleLogin
Version: 0.0.2
Summary: auto login google account by selenium chrome driver 
Home-page: https://pypi.org/project/seleniumGoogleLogin
Author: KuoYuan Li
Author-email: funny4875@gmail.com
License: UNKNOWN
Keywords: selenium,google auth,chromedriver
Platform: UNKNOWN
Classifier: License :: OSI Approved :: MIT License
Classifier: Programming Language :: Python :: 3
